fhops/__init__.py
fhops/cli/_utils.py
fhops/cli/benchmarks.py
fhops/cli/geospatial.py
fhops/cli/main.py
fhops/cli/profiles.py
fhops/cli/synthetic.py
fhops/cli/telemetry.py
fhops/core/types.py
fhops/data/loaders.py
fhops/eval/kpis.py
fhops/evaluation/__init__.py
fhops/evaluation/metrics/__init__.py
fhops/evaluation/metrics/aggregates.py
fhops/evaluation/metrics/kpis.py
fhops/evaluation/playback/__init__.py
fhops/evaluation/playback/adapters.py
fhops/evaluation/playback/aggregates.py
fhops/evaluation/playback/core.py
fhops/evaluation/playback/events.py
fhops/evaluation/playback/exporters.py
fhops/evaluation/playback/stochastic.py
fhops/evaluation/reporting/__init__.py
fhops/model/pyomo_builder.py
fhops/optimization/__init__.py
fhops/optimization/constraints/__init__.py
fhops/optimization/heuristics/__init__.py
fhops/optimization/heuristics/ils.py
fhops/optimization/heuristics/multistart.py
fhops/optimization/heuristics/registry.py
fhops/optimization/heuristics/sa.py
fhops/optimization/heuristics/tabu.py
fhops/optimization/mip/__init__.py
fhops/optimization/mip/builder.py
fhops/optimization/mip/highs_driver.py
fhops/optimization/mip/constraints/system_sequencing.py
fhops/scenario/__init__.py
fhops/scenario/contract/__init__.py
fhops/scenario/contract/models.py
fhops/scenario/io/__init__.py
fhops/scenario/io/loaders.py
fhops/scenario/io/mobilisation.py
fhops/scenario/synthetic/__init__.py
fhops/scenario/synthetic/generator.py
fhops/scheduling/__init__.py
fhops/scheduling/geospatial.py
fhops/scheduling/mobilisation/__init__.py
fhops/scheduling/mobilisation/models.py
fhops/scheduling/systems/__init__.py
fhops/scheduling/systems/models.py
fhops/scheduling/timeline/__init__.py
fhops/scheduling/timeline/models.py
fhops/solve/highs_mip.py
fhops/solve/heuristics/sa.py
fhops/telemetry/__init__.py
fhops/telemetry/jsonl.py
fhops/telemetry/run_logger.py
fhops/telemetry/sqlite_store.py
fhops-0.1.0a1.dist-info/METADATA
fhops-0.1.0a1.dist-info/WHEEL
fhops-0.1.0a1.dist-info/entry_points.txt
fhops-0.1.0a1.dist-info/licenses/LICENSE
fhops-0.1.0a1.dist-info/RECORD
