Metadata-Version: 2.4
Name: fhops
Version: 0.1.0a1
Summary: Forest Harvesting Operations Planning System
Author: UBC FRESH Lab
License: MIT
License-File: LICENSE
Requires-Python: >=3.11
Requires-Dist: highspy>=1.7.0
Requires-Dist: numpy>=1.26.0
Requires-Dist: optuna>=3.5.0
Requires-Dist: pandas>=2.2.0
Requires-Dist: pyarrow>=15.0.0
Requires-Dist: pydantic>=2.6.0
Requires-Dist: pyomo>=6.7.0
Requires-Dist: rich>=13.7.0
Requires-Dist: typer>=0.9.0
Provides-Extra: dev
Requires-Dist: black>=24.0.0; extra == 'dev'
Requires-Dist: hypothesis>=6.99.0; extra == 'dev'
Requires-Dist: mypy>=1.10.0; extra == 'dev'
Requires-Dist: pandas-stubs>=2.2.0; extra == 'dev'
Requires-Dist: pre-commit>=3.7.0; extra == 'dev'
Requires-Dist: pytest-cov>=5.0.0; extra == 'dev'
Requires-Dist: pytest>=8.0.0; extra == 'dev'
Requires-Dist: ruff>=0.4.0; extra == 'dev'
Requires-Dist: types-pyyaml>=6.0.12; extra == 'dev'
Provides-Extra: geo
Requires-Dist: geopandas>=0.14.0; extra == 'geo'
Provides-Extra: gurobi
Requires-Dist: gurobipy>=11.0.0; extra == 'gurobi'
